src/__init__.py
src/backend.py
src/const.py
src/frontend.py
src/main.py
src/utils.py
proxcat-0.3.dist-info/LICENSE
proxcat-0.3.dist-info/METADATA
proxcat-0.3.dist-info/WHEEL
proxcat-0.3.dist-info/entry_points.txt
proxcat-0.3.dist-info/top_level.txt
proxcat-0.3.dist-info/RECORD
