Metadata-Version: 2.1
Name: proxcat
Version: 0.3
Summary: local htop-like status monitor for remote Proxmox VE servers
Home-page: https://github.com/aisuneko/proxcat
Author: aisuneko
Author-email: iceneko@protonmail.ch
Maintainer: aisuneko
Maintainer-email: iceneko@protonmail.ch
License: MIT
Keywords: proxmox,proxmoxer,PVE,status,monitor
Classifier: Development Status :: 3 - Alpha
Classifier: Intended Audience :: System Administrators
Classifier: Environment :: Console :: Curses
Classifier: License :: OSI Approved :: MIT License
Classifier: Operating System :: OS Independent
Classifier: Programming Language :: Python :: 3
Classifier: Topic :: System :: Monitoring
License-File: LICENSE
Requires-Dist: requests
Requires-Dist: proxmoxer
Provides-Extra: sensors
Requires-Dist: PySensors ; extra == 'sensors'
